MANIFEST.in
README.rst
license.rst
setup.py
doc/Makefile
doc/api.rst
doc/capi.rst
doc/conf.py
doc/diff_pyopencl.rst
doc/getting_started.rst
doc/index.rst
doc/license.rst
doc/make.bat
doc/examples/example.py
doc/examples/new_types.py
examples/add_vectors.py
examples/gl_interop_demo.py
examples/print_device_info.py
opencl/__init__.py
opencl/_cl.pxd
opencl/_cl_platform.pxd
opencl/cl_header.h
opencl/cl_mem.c
opencl/cl_mem.pxd
opencl/cl_mem.pyx
opencl/cl_mem_api.h
opencl/cl_types.c
opencl/cl_types.pyx
opencl/clgl.c
opencl/clgl.pxd
opencl/clgl.pyx
opencl/clgl_compat.h
opencl/context.c
opencl/context.pxd
opencl/context.pyx
opencl/context_api.h
opencl/copencl.c
opencl/copencl.pxd
opencl/copencl.pyx
opencl/copencl_api.h
opencl/errors.c
opencl/errors.pyx
opencl/event.c
opencl/event.pxd
opencl/event.pyx
opencl/event_api.h
opencl/kernel.c
opencl/kernel.pxd
opencl/kernel.pyx
opencl/kernel_api.h
opencl/program.c
opencl/program.pxd
opencl/program.pyx
opencl/program_api.h
opencl/pyopencl.h
opencl/queue.c
opencl/queue.pxd
opencl/queue.pyx
opencl/queue_api.h
opencl/type_formats.c
opencl/type_formats.pyx
opencl/version.py
opencl/test/__init__.py
opencl/test/test_memobj.py
opencl/test/test_platform.py
opencl_for_python.egg-info/PKG-INFO
opencl_for_python.egg-info/SOURCES.txt
opencl_for_python.egg-info/dependency_links.txt
opencl_for_python.egg-info/top_level.txt