Metadata-Version: 1.0
Name: opencl-for-python
Version: 0.5.1
Summary: Open CL Python bindings
Home-page: http://srossross.github.com/oclpb
Author: Enthought, Inc.
Author-email: srossross@enthought.com
License: BSD
Platform: Windows
Platform: Linux
Platform: Mac OS-X
Platform: Unix
Platform: Solaris
Classifier: Development Status :: 5 - Production/Stable
Classifier: Intended Audience :: Developers
Classifier: Intended Audience :: Science/Research
Classifier: License :: OSI Approved :: BSD License
Classifier: Operating System :: MacOS
Classifier: Operating System :: Microsoft :: Windows
Classifier: Operating System :: OS Independent
Classifier: Operating System :: POSIX
Classifier: Operating System :: Unix
Classifier: Programming Language :: Python :: 2
Classifier: Programming Language :: Python :: 3
Classifier: Topic :: Scientific/Engineering
Classifier: Topic :: Software Development
Classifier: Topic :: Software Development :: Libraries
